custom_sastrawi/__init__.py
custom_sastrawi/Dictionary/ArrayDictionary.py
custom_sastrawi/Dictionary/DictionaryInterface.py
custom_sastrawi/Dictionary/__init__.py
custom_sastrawi/Morphology/InvalidAffixPairSpecification.py
custom_sastrawi/Morphology/__init__.py
custom_sastrawi/Morphology/Disambiguator/DisambiguatorPrefixRule1.py
custom_sastrawi/Morphology/Disambiguator/DisambiguatorPrefixRule10.py
custom_sastrawi/Morphology/Disambiguator/DisambiguatorPrefixRule11.py
custom_sastrawi/Morphology/Disambiguator/DisambiguatorPrefixRule12.py
custom_sastrawi/Morphology/Disambiguator/DisambiguatorPrefixRule13.py
custom_sastrawi/Morphology/Disambiguator/DisambiguatorPrefixRule14.py
custom_sastrawi/Morphology/Disambiguator/DisambiguatorPrefixRule15.py
custom_sastrawi/Morphology/Disambiguator/DisambiguatorPrefixRule16.py
custom_sastrawi/Morphology/Disambiguator/DisambiguatorPrefixRule17.py
custom_sastrawi/Morphology/Disambiguator/DisambiguatorPrefixRule18.py
custom_sastrawi/Morphology/Disambiguator/DisambiguatorPrefixRule19.py
custom_sastrawi/Morphology/Disambiguator/DisambiguatorPrefixRule2.py
custom_sastrawi/Morphology/Disambiguator/DisambiguatorPrefixRule20.py
custom_sastrawi/Morphology/Disambiguator/DisambiguatorPrefixRule21.py
custom_sastrawi/Morphology/Disambiguator/DisambiguatorPrefixRule23.py
custom_sastrawi/Morphology/Disambiguator/DisambiguatorPrefixRule24.py
custom_sastrawi/Morphology/Disambiguator/DisambiguatorPrefixRule25.py
custom_sastrawi/Morphology/Disambiguator/DisambiguatorPrefixRule26.py
custom_sastrawi/Morphology/Disambiguator/DisambiguatorPrefixRule27.py
custom_sastrawi/Morphology/Disambiguator/DisambiguatorPrefixRule28.py
custom_sastrawi/Morphology/Disambiguator/DisambiguatorPrefixRule29.py
custom_sastrawi/Morphology/Disambiguator/DisambiguatorPrefixRule3.py
custom_sastrawi/Morphology/Disambiguator/DisambiguatorPrefixRule30.py
custom_sastrawi/Morphology/Disambiguator/DisambiguatorPrefixRule31.py
custom_sastrawi-1.0.5.dist-info/METADATA
custom_sastrawi-1.0.5.dist-info/RECORD
custom_sastrawi-1.0.5.dist-info/WHEEL
custom_sastrawi-1.0.5.dist-info/top_level.txt
