Metadata-Version: 2.1
Name: custom-sastrawi
Version: 1.0.5
Summary: An indonesian text-mining library derived from PySastrawi (https://github.com/har07/PySastrawi) with certain modification
Home-page: https://github.com/YunazGilang/custom-sastrawi
Author: Yunaz Gilang
Author-email: yunaz.gilang@gmail.com
License: UNKNOWN
Keywords: sastrawi,custom,indonesian,text-mining
Platform: UNKNOWN
Classifier: Programming Language :: Python :: 3
Classifier: License :: OSI Approved :: MIT License
Classifier: Operating System :: OS Independent
